{
  "todos": [
    {
      "id": "1",
      "title": "1",
      "description": "2",
      "done": false,
      "order": 1
    },
    {
      "id": "2",
      "title": "2",
      "description": "3",
      "done": false,
      "order": 2
    },
    {
      "id": "3",
      "title": "4",
      "description": "5",
      "done": false,
      "order": 3
    },
    {
      "id": "4",
      "title": "1124124",
      "description": "124124",
      "done": false,
      "order": 4
    },
    {
      "id": "5",
      "title": "2252525",
      "description": "252525",
      "done": false,
      "order": 5
    },
    {
      "id": "6",
      "title": "15151",
      "description": "25125125",
      "done": false,
      "order": 6
    },
    {
      "id": "7",
      "title": "5555",
      "description": "5555",
      "done": false,
      "order": 7
    }
  ]
}