{
  "todos": [
    {
      "id": "1",
      "title": "ㅇㅇㅇ",
      "description": "ㅇㅇ유ㅠ123",
      "done": false,
      "order": 1
    },
    {
      "id": "2",
      "title": "ㅠㅠㅠㅠ",
      "description": "2131321",
      "done": false,
      "order": 2
    },
    {
      "id": "3",
      "title": "ㅇㄹㅇㄹㅇ",
      "description": "ㅇㄹㄹㄹㅇㄹ",
      "done": false,
      "order": 3
    },
    {
      "id": "4",
      "title": "ㅠㅠㅠㅠㅠ",
      "description": "ㅠㅠㅠㅠㅠㅠㅠ",
      "done": false,
      "order": 4
    },
    {
      "id": "5",
      "title": "ㅋㅋㅋ",
      "description": "ㅎㅎㅎ",
      "done": false,
      "order": 5
    }
  ]
}